README.md
butterrobot/__init__.py
butterrobot/__main__.py
butterrobot/app.py
butterrobot/config.py
butterrobot/lib/__init__.py
butterrobot/lib/slack.py
butterrobot/lib/telegram.py
butterrobot/logging.py
butterrobot/objects.py
butterrobot/platforms/__init__.py
butterrobot/platforms/base.py
butterrobot/platforms/slack.py
butterrobot/platforms/telegram.py
butterrobot/plugins.py
butterrobot_plugins_contrib/__init__.py
butterrobot_plugins_contrib/dev.py
butterrobot_plugins_contrib/fun.py
butterrobot-0.0.2a3.dist-info/entry_points.txt
butterrobot-0.0.2a3.dist-info/WHEEL
butterrobot-0.0.2a3.dist-info/METADATA
butterrobot-0.0.2a3.dist-info/RECORD
