Metadata-Version: 2.1
Name: butterrobot
Version: 0.0.2a3
Summary: What is my purpose?
License: GPL-2.0
Author: Felipe Martin
Author-email: me@fmartingr.com
Requires-Python: >=3.7,<4.0
Classifier: License :: OSI Approved :: GNU General Public License v2 (GPLv2)
Classifier: Programming Language :: Python :: 3
Classifier: Programming Language :: Python :: 3.7
Classifier: Programming Language :: Python :: 3.8
Requires-Dist: aiohttp (>=3.6.2,<4.0.0)
Requires-Dist: colorama (>=0.4.3,<0.5.0)
Requires-Dist: quart (>=0.11.3,<0.12.0)
Requires-Dist: structlog (>=20.1.0,<21.0.0)
